{
    "key": "group_69a8bc1fac0cc",
    "title": "Admin: Airtable Links",
    "fields": [
        {
            "key": "field_69a8bc1ff3da5",
            "label": "Airtable Table Configurations",
            "name": "airtable_table_configurations",
            "aria-label": "",
            "type": "group",
            "instructions": "",
            "required": 0,
            "conditional_logic": 0,
            "wrapper": {
                "width": "",
                "class": "",
                "id": ""
            },
            "layout": "block",
            "sub_fields": [
                {
                    "key": "field_69a8bc4df3da6",
                    "label": "Base ID",
                    "name": "base_id",
                    "aria-label": "",
                    "type": "text",
                    "instructions": "",
                    "required": 1,
                    "conditional_logic": 0,
                    "wrapper": {
                        "width": "",
                        "class": "",
                        "id": ""
                    },
                    "default_value": "",
                    "maxlength": "",
                    "allow_in_bindings": 0,
                    "placeholder": "appXXXXXXXXXXXXXX",
                    "prepend": "",
                    "append": ""
                },
                {
                    "key": "field_69a8bc68f3da7",
                    "label": "Languages",
                    "name": "languages",
                    "aria-label": "",
                    "type": "group",
                    "instructions": "",
                    "required": 0,
                    "conditional_logic": 0,
                    "wrapper": {
                        "width": "50",
                        "class": "",
                        "id": ""
                    },
                    "layout": "row",
                    "sub_fields": [
                        {
                            "key": "field_69a8bc79f3da8",
                            "label": "Table ID",
                            "name": "table_id",
                            "aria-label": "",
                            "type": "text",
                            "instructions": "",
                            "required": 1,
                            "conditional_logic": 0,
                            "wrapper": {
                                "width": "",
                                "class": "",
                                "id": ""
                            },
                            "default_value": "",
                            "maxlength": "",
                            "allow_in_bindings": 0,
                            "placeholder": "tblXXXXXXXXXXXXXX",
                            "prepend": "",
                            "append": ""
                        },
                        {
                            "key": "field_69a8bc7af3da9",
                            "label": "View ID",
                            "name": "view_id",
                            "aria-label": "",
                            "type": "text",
                            "instructions": "",
                            "required": 1,
                            "conditional_logic": 0,
                            "wrapper": {
                                "width": "",
                                "class": "",
                                "id": ""
                            },
                            "default_value": "",
                            "maxlength": "",
                            "allow_in_bindings": 0,
                            "placeholder": "viwXXXXXXXXXXXXXX",
                            "prepend": "",
                            "append": ""
                        }
                    ]
                },
                {
                    "key": "field_69a8bcd44275d",
                    "label": "Videos",
                    "name": "videos",
                    "aria-label": "",
                    "type": "group",
                    "instructions": "",
                    "required": 0,
                    "conditional_logic": 0,
                    "wrapper": {
                        "width": "50",
                        "class": "",
                        "id": ""
                    },
                    "layout": "row",
                    "sub_fields": [
                        {
                            "key": "field_69a8bcd44275e",
                            "label": "Table ID",
                            "name": "table_id",
                            "aria-label": "",
                            "type": "text",
                            "instructions": "",
                            "required": 1,
                            "conditional_logic": 0,
                            "wrapper": {
                                "width": "",
                                "class": "",
                                "id": ""
                            },
                            "default_value": "",
                            "maxlength": "",
                            "allow_in_bindings": 0,
                            "placeholder": "tblXXXXXXXXXXXXXX",
                            "prepend": "",
                            "append": ""
                        },
                        {
                            "key": "field_69a8bcd44275f",
                            "label": "View ID",
                            "name": "view_id",
                            "aria-label": "",
                            "type": "text",
                            "instructions": "",
                            "required": 1,
                            "conditional_logic": 0,
                            "wrapper": {
                                "width": "",
                                "class": "",
                                "id": ""
                            },
                            "default_value": "",
                            "maxlength": "",
                            "allow_in_bindings": 0,
                            "placeholder": "viwXXXXXXXXXXXXXX",
                            "prepend": "",
                            "append": ""
                        }
                    ]
                },
                {
                    "key": "field_69a8bd25c4037",
                    "label": "Lexicons",
                    "name": "lexicons",
                    "aria-label": "",
                    "type": "group",
                    "instructions": "",
                    "required": 0,
                    "conditional_logic": 0,
                    "wrapper": {
                        "width": "50",
                        "class": "",
                        "id": ""
                    },
                    "layout": "row",
                    "sub_fields": [
                        {
                            "key": "field_69a8bd25c4038",
                            "label": "Table ID",
                            "name": "table_id",
                            "aria-label": "",
                            "type": "text",
                            "instructions": "",
                            "required": 1,
                            "conditional_logic": 0,
                            "wrapper": {
                                "width": "",
                                "class": "",
                                "id": ""
                            },
                            "default_value": "",
                            "maxlength": "",
                            "allow_in_bindings": 0,
                            "placeholder": "tblXXXXXXXXXXXXXX",
                            "prepend": "",
                            "append": ""
                        },
                        {
                            "key": "field_69a8bd25c4039",
                            "label": "View ID",
                            "name": "view_id",
                            "aria-label": "",
                            "type": "text",
                            "instructions": "",
                            "required": 1,
                            "conditional_logic": 0,
                            "wrapper": {
                                "width": "",
                                "class": "",
                                "id": ""
                            },
                            "default_value": "",
                            "maxlength": "",
                            "allow_in_bindings": 0,
                            "placeholder": "viwXXXXXXXXXXXXXX",
                            "prepend": "",
                            "append": ""
                        }
                    ]
                },
                {
                    "key": "field_69a8bd1bc4034",
                    "label": "Captions",
                    "name": "captions",
                    "aria-label": "",
                    "type": "group",
                    "instructions": "",
                    "required": 0,
                    "conditional_logic": 0,
                    "wrapper": {
                        "width": "50",
                        "class": "",
                        "id": ""
                    },
                    "layout": "row",
                    "sub_fields": [
                        {
                            "key": "field_69a8bd1bc4035",
                            "label": "Table ID",
                            "name": "table_id",
                            "aria-label": "",
                            "type": "text",
                            "instructions": "",
                            "required": 1,
                            "conditional_logic": 0,
                            "wrapper": {
                                "width": "",
                                "class": "",
                                "id": ""
                            },
                            "default_value": "",
                            "maxlength": "",
                            "allow_in_bindings": 0,
                            "placeholder": "tblXXXXXXXXXXXXXX",
                            "prepend": "",
                            "append": ""
                        },
                        {
                            "key": "field_69a8bd1bc4036",
                            "label": "View ID",
                            "name": "view_id",
                            "aria-label": "",
                            "type": "text",
                            "instructions": "",
                            "required": 1,
                            "conditional_logic": 0,
                            "wrapper": {
                                "width": "",
                                "class": "",
                                "id": ""
                            },
                            "default_value": "",
                            "maxlength": "",
                            "allow_in_bindings": 0,
                            "placeholder": "viwXXXXXXXXXXXXXX",
                            "prepend": "",
                            "append": ""
                        }
                    ]
                }
            ]
        }
    ],
    "location": [
        [
            {
                "param": "options_page",
                "operator": "==",
                "value": "airtable-link"
            }
        ],
        [
            {
                "param": "options_page",
                "operator": "==",
                "value": "airtable-links"
            }
        ]
    ],
    "menu_order": 0,
    "position": "normal",
    "style": "default",
    "label_placement": "top",
    "instruction_placement": "label",
    "hide_on_screen": "",
    "active": true,
    "description": "",
    "show_in_rest": 0,
    "display_title": "",
    "modified": 1772666545
}
